anki_deck_librarian/__init__.py
anki_deck_librarian/cli.py
anki_deck_librarian/loader.py
anki_deck_librarian/schemas.py
anki_deck_librarian-0.1.2.dist-info/LICENSE.md
anki_deck_librarian-0.1.2.dist-info/METADATA
anki_deck_librarian-0.1.2.dist-info/WHEEL
anki_deck_librarian-0.1.2.dist-info/entry_points.txt
anki_deck_librarian-0.1.2.dist-info/top_level.txt
anki_deck_librarian-0.1.2.dist-info/RECORD
