Metadata-Version: 2.1
Name: anki-deck-librarian
Version: 0.1.2
Summary: A library/CLI for generating anki decks from YAML
Author-email: Raymond Berg <dev@raymondberg.com>
License: GNU AFFERO GENERAL PUBLIC LICENSE
Project-URL: Homepage, https://github.com/raymondberg/anki-deck-librarian
Keywords: anki,deck,cards,flashcards,yaml
Classifier: License :: OSI Approved :: MIT License
Classifier: Programming Language :: Python
Classifier: Programming Language :: Python :: 3
Requires-Python: >=3.9
License-File: LICENSE.md
Requires-Dist: genanki
Requires-Dist: pydantic
Requires-Dist: ruamel.yaml
Requires-Dist: typer
Provides-Extra: dev
Requires-Dist: black ; extra == 'dev'
Requires-Dist: isort ; extra == 'dev'
